walnutpi/__init__.py
walnutpi-1.0.1.dist-info/METADATA
walnutpi-1.0.1.dist-info/WHEEL
walnutpi-1.0.1.dist-info/licenses/LICENSE
walnutpi-1.0.1.dist-info/RECORD
